adspower/__init__.py
adspower/adspowerapi.py
adspower/adspowerclean.py
adspower/adspowermanager.py
adspower/settings.py
adspower/spider.py
adspower/utils.py
adspower_sdk-0.1.8.dist-info/licenses/LICENSE
adspower_sdk-0.1.8.dist-info/METADATA
adspower_sdk-0.1.8.dist-info/WHEEL
adspower_sdk-0.1.8.dist-info/top_level.txt
adspower_sdk-0.1.8.dist-info/RECORD
