Metadata-Version: 2.4
Name: adspower-sdk
Version: 0.1.8
Summary: A Python SDK for interacting with AdsPower API
Home-page: https://github.com/liweilijie/adspower-sdk
Author: Wei Li
Author-email: liweilijie@gmail.com
License: MIT
Classifier: Programming Language :: Python :: 3
Classifier: License :: OSI Approved :: MIT License
Classifier: Operating System :: OS Independent
Requires-Python: >=3.6
License-File: LICENSE
Requires-Dist: httpx
Dynamic: license-file
